MANIFEST.in
README.rst
setup.py
collective/__init__.py
collective.z3cform.keywordwidget.egg-info/PKG-INFO
collective.z3cform.keywordwidget.egg-info/SOURCES.txt
collective.z3cform.keywordwidget.egg-info/dependency_links.txt
collective.z3cform.keywordwidget.egg-info/entry_points.txt
collective.z3cform.keywordwidget.egg-info/namespace_packages.txt
collective.z3cform.keywordwidget.egg-info/not-zip-safe
collective.z3cform.keywordwidget.egg-info/requires.txt
collective.z3cform.keywordwidget.egg-info/top_level.txt
collective/z3cform/__init__.py
collective/z3cform/keywordwidget/README.txt
collective/z3cform/keywordwidget/__init__.py
collective/z3cform/keywordwidget/configure.zcml
collective/z3cform/keywordwidget/field.py
collective/z3cform/keywordwidget/handler.py
collective/z3cform/keywordwidget/inoutkeyword_display.pt
collective/z3cform/keywordwidget/inoutkeyword_input.pt
collective/z3cform/keywordwidget/interfaces.py
collective/z3cform/keywordwidget/keyword_display.pt
collective/z3cform/keywordwidget/keyword_input.pt
collective/z3cform/keywordwidget/testing.py
collective/z3cform/keywordwidget/tests.py
collective/z3cform/keywordwidget/widget.py
collective/z3cform/keywordwidget/profiles/testing/catalog.xml
docs/HISTORY.txt