Metadata-Version: 1.1
Name: collective.z3cform.keywordwidget
Version: 1.3
Summary: Adds a keyword widget (similar to to Archetypes.Widget:KeywordWidget) to z3cform.
Home-page: http://pypi.python.org/pypi/collective.z3cform.keywordwidget
Author: JC Brand
Author-email: brand@syslab.com
License: GPL
Keywords: syslab keyword widget keywordwidget z3cform
Platform: UNKNOWN
Classifier: Programming Language :: Python
Classifier: Topic :: Software Development :: Libraries :: Python Modules
